tddschn_utils/__init__.py
tddschn_utils/gpt_plain_text_file_loader.py
tddschn_utils/webvtt2txt.py
tddschn_utils-1.0.1.dist-info/METADATA
tddschn_utils-1.0.1.dist-info/WHEEL
tddschn_utils-1.0.1.dist-info/entry_points.txt
tddschn_utils-1.0.1.dist-info/RECORD
